{
	"$schema": "http://schema.management.azure.com/schemas/2015-01-01/deploymentTemplate.json#",
	"contentVersion": "1.0.0.0",
	"parameters": {
		"factoryName": {
			"type": "string",
			"metadata": "Data Factory name",
			"defaultValue": "adf-Corp-DataPlatform-Prod"
		},
		"azsql_bdConsolidado_connectionString": {
			"type": "secureString",
			"metadata": "Secure string for 'connectionString' of 'azsql_bdConsolidado'"
		},
		"blob_Cargas_DataFactory_connectionString": {
			"type": "secureString",
			"metadata": "Secure string for 'connectionString' of 'blob_Cargas_DataFactory'"
		},
		"mssql_Smart_Dayhorc_connectionString": {
			"type": "secureString",
			"metadata": "Secure string for 'connectionString' of 'mssql_Smart_Dayhorc'"
		},
		"mssql_Smart_HOSL_connectionString": {
			"type": "secureString",
			"metadata": "Secure string for 'connectionString' of 'mssql_Smart_HOSL'"
		},
		"ora_Tasy_Cloud_connectionString": {
			"type": "secureString",
			"metadata": "Secure string for 'connectionString' of 'ora_Tasy_Cloud'"
		},
		"ora_Tasy_Sadalla_connectionString": {
			"type": "secureString",
			"metadata": "Secure string for 'connectionString' of 'ora_Tasy_Sadalla'"
		},
		"kv_Credentials_properties_typeProperties_baseUrl": {
			"type": "string",
			"defaultValue": "https://Corp-Credentials.vault.azure.net/"
		}
	},
	"variables": {
		"factoryId": "[concat('Microsoft.DataFactory/factories/', parameters('factoryName'))]"
	},
	"resources": [
		{
			"name": "[concat(parameters('factoryName'), '/kv_Credentials')]",
			"type": "Microsoft.DataFactory/factories/linkedServices",
			"apiVersion": "2018-06-01",
			"properties": {
				"annotations": [],
				"type": "AzureKeyVault",
				"typeProperties": {
					"baseUrl": "[parameters('kv_Credentials_properties_typeProperties_baseUrl')]"
				}
			},
			"dependsOn": []
		},
		{
			"name": "[concat(parameters('factoryName'), '/ir-vm-DataPlatform')]",
			"type": "Microsoft.DataFactory/factories/integrationRuntimes",
			"apiVersion": "2018-06-01",
			"properties": {
				"type": "SelfHosted",
				"typeProperties": {}
			},
			"dependsOn": []
		},
		{
			"name": "[concat(parameters('factoryName'), '/azsql_bdConsolidado')]",
			"type": "Microsoft.DataFactory/factories/linkedServices",
			"apiVersion": "2018-06-01",
			"properties": {
				"annotations": [],
				"type": "AzureSqlDatabase",
				"typeProperties": {
					"connectionString": "[parameters('azsql_bdConsolidado_connectionString')]",
					"password": {
						"type": "AzureKeyVaultSecret",
						"store": {
							"referenceName": "kv_Credentials",
							"type": "LinkedServiceReference"
						},
						"secretName": "cred-admsql-azure"
					}
				}
			},
			"dependsOn": [
				"[concat(variables('factoryId'), '/linkedServices/kv_Credentials')]"
			]
		},
		{
			"name": "[concat(parameters('factoryName'), '/blob_Cargas_DataFactory')]",
			"type": "Microsoft.DataFactory/factories/linkedServices",
			"apiVersion": "2018-06-01",
			"properties": {
				"annotations": [],
				"type": "AzureBlobStorage",
				"typeProperties": {
					"connectionString": "[parameters('blob_Cargas_DataFactory_connectionString')]",
					"accountKey": {
						"type": "AzureKeyVaultSecret",
						"store": {
							"referenceName": "kv_Credentials",
							"type": "LinkedServiceReference"
						},
						"secretName": "cred-sto-cargas-accesskey"
					}
				}
			},
			"dependsOn": [
				"[concat(variables('factoryId'), '/linkedServices/kv_Credentials')]"
			]
		},
		{
			"name": "[concat(parameters('factoryName'), '/mssql_Smart_Dayhorc')]",
			"type": "Microsoft.DataFactory/factories/linkedServices",
			"apiVersion": "2018-06-01",
			"properties": {
				"annotations": [],
				"type": "SqlServer",
				"typeProperties": {
					"connectionString": "[parameters('mssql_Smart_Dayhorc_connectionString')]",
					"password": {
						"type": "AzureKeyVaultSecret",
						"store": {
							"referenceName": "kv_Credentials",
							"type": "LinkedServiceReference"
						},
						"secretName": "cred-admsql-dayhorc"
					}
				},
				"connectVia": {
					"referenceName": "ir-vm-DataPlatform",
					"type": "IntegrationRuntimeReference"
				}
			},
			"dependsOn": [
				"[concat(variables('factoryId'), '/integrationRuntimes/ir-vm-DataPlatform')]",
				"[concat(variables('factoryId'), '/linkedServices/kv_Credentials')]"
			]
		},
		{
			"name": "[concat(parameters('factoryName'), '/mssql_Smart_HOSL')]",
			"type": "Microsoft.DataFactory/factories/linkedServices",
			"apiVersion": "2018-06-01",
			"properties": {
				"annotations": [],
				"type": "SqlServer",
				"typeProperties": {
					"connectionString": "[parameters('mssql_Smart_HOSL_connectionString')]",
					"password": {
						"type": "AzureKeyVaultSecret",
						"store": {
							"referenceName": "kv_Credentials",
							"type": "LinkedServiceReference"
						},
						"secretName": "cred-admsql-hosl"
					}
				},
				"connectVia": {
					"referenceName": "ir-vm-DataPlatform",
					"type": "IntegrationRuntimeReference"
				}
			},
			"dependsOn": [
				"[concat(variables('factoryId'), '/integrationRuntimes/ir-vm-DataPlatform')]",
				"[concat(variables('factoryId'), '/linkedServices/kv_Credentials')]"
			]
		},
		{
			"name": "[concat(parameters('factoryName'), '/ora_Tasy_Cloud')]",
			"type": "Microsoft.DataFactory/factories/linkedServices",
			"apiVersion": "2018-06-01",
			"properties": {
				"annotations": [],
				"type": "Oracle",
				"typeProperties": {
					"connectionString": "[parameters('ora_Tasy_Cloud_connectionString')]",
					"password": {
						"type": "AzureKeyVaultSecret",
						"store": {
							"referenceName": "kv_Credentials",
							"type": "LinkedServiceReference"
						},
						"secretName": "cred-admora-tasy"
					}
				},
				"connectVia": {
					"referenceName": "ir-vm-DataPlatform",
					"type": "IntegrationRuntimeReference"
				}
			},
			"dependsOn": [
				"[concat(variables('factoryId'), '/integrationRuntimes/ir-vm-DataPlatform')]",
				"[concat(variables('factoryId'), '/linkedServices/kv_Credentials')]"
			]
		},
		{
			"name": "[concat(parameters('factoryName'), '/ora_Tasy_Sadalla')]",
			"type": "Microsoft.DataFactory/factories/linkedServices",
			"apiVersion": "2018-06-01",
			"properties": {
				"annotations": [],
				"type": "Oracle",
				"typeProperties": {
					"connectionString": "[parameters('ora_Tasy_Sadalla_connectionString')]",
					"password": {
						"type": "AzureKeyVaultSecret",
						"store": {
							"referenceName": "kv_Credentials",
							"type": "LinkedServiceReference"
						},
						"secretName": "cred-admora-tasy"
					}
				},
				"connectVia": {
					"referenceName": "ir-vm-DataPlatform",
					"type": "IntegrationRuntimeReference"
				}
			},
			"dependsOn": [
				"[concat(variables('factoryId'), '/integrationRuntimes/ir-vm-DataPlatform')]",
				"[concat(variables('factoryId'), '/linkedServices/kv_Credentials')]"
			]
		},
		{
			"name": "[concat(parameters('factoryName'), '/blob_Unidades')]",
			"type": "Microsoft.DataFactory/factories/datasets",
			"apiVersion": "2018-06-01",
			"properties": {
				"linkedServiceName": {
					"referenceName": "blob_Cargas_DataFactory",
					"type": "LinkedServiceReference"
				},
				"folder": {
					"name": "Blob Storage"
				},
				"annotations": [],
				"type": "DelimitedText",
				"typeProperties": {
					"location": {
						"type": "AzureBlobStorageLocation",
						"fileName": "unidade_negocio.CSV",
						"container": "cadastrosgerais"
					},
					"columnDelimiter": ";",
					"escapeChar": "\\",
					"firstRowAsHeader": true,
					"quoteChar": "\""
				},
				"schema": [
					{
						"name": "#",
						"type": "String"
					},
					{
						"name": "HIERARQUIA",
						"type": "String"
					},
					{
						"name": "CNPJ",
						"type": "String"
					},
					{
						"name": "RAZAO_SOCIAL",
						"type": "String"
					},
					{
						"name": "ENDERECO",
						"type": "String"
					},
					{
						"name": "BAIRRO",
						"type": "String"
					},
					{
						"name": "CIDADE",
						"type": "String"
					},
					{
						"name": "CEP",
						"type": "String"
					}
				]
			},
			"dependsOn": [
				"[concat(variables('factoryId'), '/linkedServices/blob_Cargas_DataFactory')]"
			]
		},
		{
			"name": "[concat(parameters('factoryName'), '/tabela_unidade_negocio')]",
			"type": "Microsoft.DataFactory/factories/datasets",
			"apiVersion": "2018-06-01",
			"properties": {
				"linkedServiceName": {
					"referenceName": "azsql_bdConsolidado",
					"type": "LinkedServiceReference"
				},
				"annotations": [],
				"type": "AzureSqlTable",
				"schema": [
					{
						"name": "cnpj",
						"type": "varchar"
					},
					{
						"name": "razao_social",
						"type": "varchar"
					},
					{
						"name": "endereco",
						"type": "varchar"
					},
					{
						"name": "bairro",
						"type": "varchar"
					},
					{
						"name": "cidade",
						"type": "varchar"
					},
					{
						"name": "cep",
						"type": "varchar"
					},
					{
						"name": "hierarquia",
						"type": "varchar"
					},
					{
						"name": "data_processamento",
						"type": "datetime",
						"precision": 23,
						"scale": 3
					}
				],
				"typeProperties": {
					"schema": "dbo",
					"table": "unidade_negocio"
				}
			},
			"dependsOn": [
				"[concat(variables('factoryId'), '/linkedServices/azsql_bdConsolidado')]"
			]
		},
		{
			"name": "[concat(parameters('factoryName'), '/pipe_unidade_negocio')]",
			"type": "Microsoft.DataFactory/factories/pipelines",
			"apiVersion": "2018-06-01",
			"properties": {
				"activities": [
					{
						"name": "task-Copia-Unidades",
						"type": "Copy",
						"dependsOn": [],
						"policy": {
							"timeout": "7.00:00:00",
							"retry": 0,
							"retryIntervalInSeconds": 30,
							"secureOutput": false,
							"secureInput": false
						},
						"userProperties": [],
						"typeProperties": {
							"source": {
								"type": "DelimitedTextSource",
								"storeSettings": {
									"type": "AzureBlobStorageReadSettings",
									"recursive": true
								},
								"formatSettings": {
									"type": "DelimitedTextReadSettings"
								}
							},
							"sink": {
								"type": "AzureSqlSink",
								"preCopyScript": "TRUNCATE TABLE dbo.unidade_negocio",
								"disableMetricsCollection": false
							},
							"enableStaging": false,
							"enableSkipIncompatibleRow": true,
							"translator": {
								"type": "TabularTranslator",
								"mappings": [
									{
										"source": {
											"name": "CNPJ",
											"type": "String"
										},
										"sink": {
											"name": "cnpj",
											"type": "String"
										}
									},
									{
										"source": {
											"name": "RAZAO_SOCIAL",
											"type": "String"
										},
										"sink": {
											"name": "razao_social",
											"type": "String"
										}
									},
									{
										"source": {
											"name": "ENDERECO",
											"type": "String"
										},
										"sink": {
											"name": "endereco",
											"type": "String"
										}
									},
									{
										"source": {
											"name": "BAIRRO",
											"type": "String"
										},
										"sink": {
											"name": "bairro",
											"type": "String"
										}
									},
									{
										"source": {
											"name": "CIDADE",
											"type": "String"
										},
										"sink": {
											"name": "cidade",
											"type": "String"
										}
									},
									{
										"source": {
											"name": "CEP",
											"type": "String"
										},
										"sink": {
											"name": "cep",
											"type": "String"
										}
									},
									{
										"source": {
											"name": "HIERARQUIA",
											"type": "String"
										},
										"sink": {
											"name": "hierarquia",
											"type": "String"
										}
									}
								]
							}
						},
						"inputs": [
							{
								"referenceName": "blob_Unidades",
								"type": "DatasetReference",
								"parameters": {}
							}
						],
						"outputs": [
							{
								"referenceName": "tabela_unidade_negocio",
								"type": "DatasetReference",
								"parameters": {}
							}
						]
					}
				],
				"folder": {
					"name": "Logic Apps Triggers"
				},
				"annotations": []
			},
			"dependsOn": [
				"[concat(variables('factoryId'), '/datasets/blob_Unidades')]",
				"[concat(variables('factoryId'), '/datasets/tabela_unidade_negocio')]"
			]
		}
	]
}